.pylintrc
.yamllint.yaml
ACKNOWLEDGEMENTS
AUTHORS
LICENSE
MANIFEST.in
README
appveyor.yml
dependencies.ini
dtfabric.ini
requirements.txt
run_tests.py
setup.cfg
setup.py
test_dependencies.ini
test_requirements.txt
tox.ini
.github/workflows/test_docker.yml
.github/workflows/test_docs.yml
.github/workflows/test_tox.yml
config/appveyor/install.ps1
config/appveyor/install.sh
config/appveyor/runtests.sh
config/dpkg/changelog
config/dpkg/clean
config/dpkg/compat
config/dpkg/control
config/dpkg/copyright
config/dpkg/dtfabric-data.dirs
config/dpkg/dtfabric-data.install
config/dpkg/python-dtfabric.install
config/dpkg/python3-dtfabric.install
config/dpkg/rules
config/dpkg/source/format
config/pylint/spelling-private-dict
docs/conf.py
docs/index.rst
docs/requirements.txt
docs/sources/Format-specification.md
docs/sources/api/dtfabric.rst
docs/sources/api/dtfabric.runtime.rst
docs/sources/api/modules.rst
docs/sources/user/Installation-instructions.md
docs/sources/user/index.rst
dtfabric/__init__.py
dtfabric/data_types.py
dtfabric/decorators.py
dtfabric/definitions.py
dtfabric/errors.py
dtfabric/reader.py
dtfabric/registry.py
dtfabric.egg-info/PKG-INFO
dtfabric.egg-info/SOURCES.txt
dtfabric.egg-info/dependency_links.txt
dtfabric.egg-info/requires.txt
dtfabric.egg-info/top_level.txt
dtfabric/runtime/__init__.py
dtfabric/runtime/byte_operations.py
dtfabric/runtime/data_maps.py
dtfabric/runtime/fabric.py
dtfabric/runtime/runtime.py
scripts/validate-definitions.py
test_data/.structure_with_string.yaml.swp
test_data/Notepad.lnk
test_data/boolean.yaml
test_data/character.yaml
test_data/constant.yaml
test_data/enumeration.yaml
test_data/floating-point.yaml
test_data/format.yaml
test_data/integer.yaml
test_data/padding.yaml
test_data/sequence.yaml
test_data/sequence_with_context.yaml
test_data/sequence_with_structure.yaml
test_data/stream.yaml
test_data/string.yaml
test_data/string_array.yaml
test_data/structure.yaml
test_data/structure_family.yaml
test_data/structure_group.yaml
test_data/structure_with_condition.yaml
test_data/structure_with_context.yaml
test_data/structure_with_padding.yaml
test_data/structure_with_section.yaml
