Metadata-Version: 2.1
Name: dtfabric
Version: 20230518
Summary: Data type fabric (dtfabric)
Home-page: https://github.com/libyal/dtfabric
Maintainer: Joachim Metz
Maintainer-email: joachim.metz@gmail.com
License: Apache License, Version 2.0
Classifier: Development Status :: 3 - Alpha
Classifier: Environment :: Console
Classifier: Operating System :: OS Independent
Classifier: Programming Language :: Python
License-File: LICENSE
